package com.example.demo.jvm;

/**
 * @ClassName: IntandFloatTest
 * @program: projectDemo
 * @Description: TODO
 * @Author: admin
 * @Date: 2020-05-01 10:41
 * @Version: 1.0
 **/
public class IntandFloatTest {

    private final int a = 10;
    private final int b = 10;
    //private int c = 20;
    private float c = 11f;
    private float d = 11f;
    private float e = 11f;

}

//警告: 二进制文件IntandFloatTest包含com.example.demo.jvm.IntandFloatTest
//        Classfile /Users/daisy/java/github/projectDemo/demo/target/classes/com/example/demo/jvm/IntandFloatTest.class
//Last modified 2020-5-1; size 522 bytes
//        MD5 checksum e73b3987c71d5a242e26e93f0d4bd586
//        Compiled from "IntandFloatTest.java"
//public class com.example.demo.jvm.IntandFloatTest
//        minor version: 0
//        major version: 52
//        flags: ACC_PUBLIC, ACC_SUPER
//        Constant pool:
//        #1 = Methodref          #9.#28         // java/lang/Object."<init>":()V
//        #2 = Fieldref           #8.#29         // com/example/demo/jvm/IntandFloatTest.a:I
//        #3 = Fieldref           #8.#30         // com/example/demo/jvm/IntandFloatTest.b:I
//        #4 = Float              11.0f
//        #5 = Fieldref           #8.#31         // com/example/demo/jvm/IntandFloatTest.c:F
//        #6 = Fieldref           #8.#32         // com/example/demo/jvm/IntandFloatTest.d:F
//        #7 = Fieldref           #8.#33         // com/example/demo/jvm/IntandFloatTest.e:F
//        #8 = Class              #34            // com/example/demo/jvm/IntandFloatTest
//        #9 = Class              #35            // java/lang/Object
//        #10 = Utf8               a
//        #11 = Utf8               I
//        #12 = Utf8               ConstantValue
//        #13 = Integer            10
//        #14 = Utf8               b
//        #15 = Utf8               c
//        #16 = Utf8               F
//        #17 = Utf8               d
//        #18 = Utf8               e
//        #19 = Utf8               <init>
//  #20 = Utf8               ()V
//          #21 = Utf8               Code
//          #22 = Utf8               LineNumberTable
//          #23 = Utf8               LocalVariableTable
//          #24 = Utf8               this
//          #25 = Utf8               Lcom/example/demo/jvm/IntandFloatTest;
//          #26 = Utf8               SourceFile
//          #27 = Utf8               IntandFloatTest.java
//          #28 = NameAndType        #19:#20        // "<init>":()V
//          #29 = NameAndType        #10:#11        // a:I
//          #30 = NameAndType        #14:#11        // b:I
//          #31 = NameAndType        #15:#16        // c:F
//          #32 = NameAndType        #17:#16        // d:F
//          #33 = NameAndType        #18:#16        // e:F
//          #34 = Utf8               com/example/demo/jvm/IntandFloatTest
//          #35 = Utf8               java/lang/Object
//          {
//public com.example.demo.jvm.IntandFloatTest();
//        descriptor: ()V
//        flags: ACC_PUBLIC
//        Code:
//        stack=2, locals=1, args_size=1
//        0: aload_0
//        1: invokespecial #1                  // Method java/lang/Object."<init>":()V
//        4: aload_0
//        5: bipush        10
//        7: putfield      #2                  // Field a:I
//        10: aload_0
//        11: bipush        10
//        13: putfield      #3                  // Field b:I
//        16: aload_0
//        17: ldc           #4                  // float 11.0f
//        19: putfield      #5                  // Field c:F
//        22: aload_0
//        23: ldc           #4                  // float 11.0f
//        25: putfield      #6                  // Field d:F
//        28: aload_0
//        29: ldc           #4                  // float 11.0f
//        31: putfield      #7                  // Field e:F
//        34: return
//        LineNumberTable:
//        line 11: 0
//        line 13: 4
//        line 14: 10
//        line 16: 16
//        line 17: 22
//        line 18: 28
//        LocalVariableTable:
//        Start  Length  Slot  Name   Signature
//        0      35     0  this   Lcom/example/demo/jvm/IntandFloatTest;
//        }
//        SourceFile: "IntandFloatTest.java"
